.DS_Store
pytc_gui/__init__.py
pytc_gui/exp_setup.py
pytc_gui/fit_update.py
pytc_gui/help_dialogs.py
pytc_gui/main_window.py
pytc_gui/exp_frames/__init__.py
pytc_gui/exp_frames/base.py
pytc_gui/exp_frames/connectors_box.py
pytc_gui/exp_frames/global_box.py
pytc_gui/exp_frames/local_box.py
pytc_gui/slider_popup/__init__.py
pytc_gui/slider_popup/base.py
pytc_gui/slider_popup/connector_popup.py
pytc_gui/slider_popup/global_popup.py
pytc_gui/slider_popup/local_popup.py
pytc_gui/sliders/__init__.py
pytc_gui/sliders/add_global_connector.py
pytc_gui/sliders/base.py
pytc_gui/sliders/global_sliders.py
pytc_gui/sliders/local_sliders.py
pytc_gui-1.0.1.dist-info/DESCRIPTION.rst
pytc_gui-1.0.1.dist-info/METADATA
pytc_gui-1.0.1.dist-info/RECORD
pytc_gui-1.0.1.dist-info/WHEEL
pytc_gui-1.0.1.dist-info/entry_points.txt
pytc_gui-1.0.1.dist-info/metadata.json
pytc_gui-1.0.1.dist-info/top_level.txt
