Metadata-Version: 2.0
Name: pytc-gui
Version: 1.0.1
Summary: PyQt5 GUI for pytc API
Home-page: https://github.com/harmslab/pytc-gui
Author: Hiranmayi Duvvuri
Author-email: hiranmayid8@gmail.com
License: UNKNOWN
Download-URL: https://github.com/harmslab/pytc-gui/tarball/1.0.0
Platform: UNKNOWN
Classifier: Programming Language :: Python
Requires-Dist: pyqt5
Requires-Dist: pytc-fitter
Requires-Dist: seaborn
